pyneuphonic/__init__.py
pyneuphonic/_agents.py
pyneuphonic/_endpoint.py
pyneuphonic/_longform_inference.py
pyneuphonic/_sse.py
pyneuphonic/_utils.py
pyneuphonic/_voices.py
pyneuphonic/_websocket.py
pyneuphonic/agents.py
pyneuphonic/client.py
pyneuphonic/models.py
pyneuphonic/player.py
pyneuphonic-1.8.8.dist-info/METADATA
pyneuphonic-1.8.8.dist-info/WHEEL
pyneuphonic-1.8.8.dist-info/licenses/LICENSE.txt
pyneuphonic-1.8.8.dist-info/RECORD
