Metadata-Version: 2.4
Name: pyneuphonic
Version: 1.8.8
Summary: A python SDK for the Neuphonic TTS Engine.
License: MIT
License-File: LICENSE.txt
Author: Neuphonic
Author-email: support@neuphonic.com
Requires-Python: >=3.9,<4.0
Classifier: License :: OSI Approved :: MIT License
Classifier: Programming Language :: Python :: 3
Classifier: Programming Language :: Python :: 3.9
Classifier: Programming Language :: Python :: 3.10
Classifier: Programming Language :: Python :: 3.11
Classifier: Programming Language :: Python :: 3.12
Classifier: Programming Language :: Python :: 3.13
Classifier: Programming Language :: Python :: 3.14
Requires-Dist: aioconsole (>=0.7.1,<0.8.0)
Requires-Dist: certifi (>=2025.6.15)
Requires-Dist: httpx (>=0.27.2,<0.28.0)
Requires-Dist: pydantic (>=2.9.2,<3.0.0)
Requires-Dist: websockets (>=14.0,<16.0)
